endterm/__init__.py
endterm/classes.py
endterm-0.0.1.dist-info/LICENSE
endterm-0.0.1.dist-info/METADATA
endterm-0.0.1.dist-info/WHEEL
endterm-0.0.1.dist-info/top_level.txt
endterm-0.0.1.dist-info/RECORD
