Metadata-Version: 2.1
Name: endterm
Version: 0.0.1
Summary: A small example package for aitu magistrants
Home-page: UNKNOWN
Author: Unknown
License: UNKNOWN
Platform: UNKNOWN
Classifier: Programming Language :: Python :: 3
Classifier: License :: OSI Approved :: MIT License
Classifier: Operating System :: OS Independent
License-File: LICENSE
Requires-Dist: py7zr
Requires-Dist: xlrd
Requires-Dist: openpyxl
Requires-Dist: pandas
Requires-Dist: importlib ; python_version == "3.6"
